m3u8_to_mp4/__init__.py
m3u8_to_mp4/exceptions.py
m3u8_to_mp4/m3u8.py
py_m3u8_to_mp4-1.1.dist-info/LICENSE
py_m3u8_to_mp4-1.1.dist-info/METADATA
py_m3u8_to_mp4-1.1.dist-info/WHEEL
py_m3u8_to_mp4-1.1.dist-info/top_level.txt
py_m3u8_to_mp4-1.1.dist-info/RECORD
