Metadata-Version: 2.1
Name: py-m3u8-to-mp4
Version: 1.1
Summary: Python package to convert m3u8 playlists to mp4 videos using FFMPEG
Home-page: https://github.com/olivialba
Author: Alba (Alberto Olivi)
Author-email: olivialberto02@gmail.com
License: MIT
Keywords: m3u8,mp4,python,m3u8 to mp4,convert m3u8,playlist
Classifier: Development Status :: 2 - Pre-Alpha
Classifier: Intended Audience :: Developers
Classifier: Programming Language :: Python :: 3
Classifier: Operating System :: Unix
Classifier: Operating System :: MacOS :: MacOS X
Classifier: Operating System :: Microsoft :: Windows
License-File: LICENSE
Requires-Dist: requests
Requires-Dist: ffmpeg-python
